Dezirteer-0.1.0.dist-info/METADATA
Dezirteer-0.1.0.dist-info/RECORD
Dezirteer-0.1.0.dist-info/WHEEL
Dezirteer-0.1.0.dist-info/top_level.txt
dezirteer/__init__.py
dezirteer/const.py
dezirteer/gui_support.py
dezirteer/main_gui.py
dezirteer/math_module.py
