Metadata-Version: 2.1
Name: Dezirteer
Version: 0.1.0
Summary: Package for dezirteer.com
Home-page: https://github.com/dazdraperma/dezirteer
Author: Vladislav Powerman
Author-email: vladislav.powerman@gmail.com
License: The MIT License (MIT)
Requires-Dist: matplotlib
Requires-Dist: scipy
